{
  "Name": "azure-security-attestation",
  "Version": "1.1.35",
  "DevVersion": null,
  "DirectoryPath": "sdk/attestation/azure-security-attestation",
  "ServiceDirectory": "attestation",
  "ReadMePath": "sdk/attestation/azure-security-attestation/README.md",
  "ChangeLogPath": "sdk/attestation/azure-security-attestation/CHANGELOG.md",
  "Group": "com.azure",
  "SdkType": "client",
  "IsNewSdk": true,
  "ArtifactName": "azure-security-attestation",
  "ReleaseStatus": "2025-08-21",
  "IncludedForValidation": false,
  "AdditionalValidationPackages": null,
  "ArtifactDetails": {
    "releaseInBatch": "${{ parameters.release_azuresecurityattestation }}",
    "triggeringPaths": [
      "/sdk/attestation/ci.yml"
    ],
    "safeName": "azuresecurityattestation",
    "groupId": "com.azure",
    "name": "azure-security-attestation"
  },
  "CIParameters": {
    "CIMatrixConfigs": []
  },
  "Namespaces": [
    "com.azure.security.attestation",
    "com.azure.security.attestation.models"
  ],
  "CIMatrixConfigs": [],
  "DependentPackages": null
}
