{
  "Name": "azure-resourcemanager-dns",
  "Version": "2.53.6",
  "DevVersion": null,
  "DirectoryPath": "sdk/dns/azure-resourcemanager-dns",
  "ServiceDirectory": "dns",
  "ReadMePath": "sdk/dns/azure-resourcemanager-dns/README.md",
  "ChangeLogPath": "sdk/dns/azure-resourcemanager-dns/CHANGELOG.md",
  "Group": "com.azure.resourcemanager",
  "SdkType": "mgmt",
  "IsNewSdk": true,
  "ArtifactName": "azure-resourcemanager-dns",
  "ReleaseStatus": "2026-01-29",
  "IncludedForValidation": false,
  "AdditionalValidationPackages": null,
  "ArtifactDetails": {
    "triggeringPaths": [
      "/sdk/dns/ci.yml"
    ],
    "groupId": "com.azure.resourcemanager",
    "safeName": "azureresourcemanagerdns",
    "name": "azure-resourcemanager-dns",
    "releaseInBatch": "${{ parameters.release_azureresourcemanagerdns }}"
  },
  "CIParameters": {
    "CIMatrixConfigs": []
  },
  "SpecProjectPath": null,
  "Namespaces": [
    "com.azure.resourcemanager.dns",
    "com.azure.resourcemanager.dns.fluent",
    "com.azure.resourcemanager.dns.fluent.models",
    "com.azure.resourcemanager.dns.models"
  ],
  "CIMatrixConfigs": [],
  "DependentPackages": null
}
