{
  "Name": "azure-mixedreality-authentication",
  "Version": "1.2.38",
  "DevVersion": null,
  "DirectoryPath": "sdk/mixedreality/azure-mixedreality-authentication",
  "ServiceDirectory": "mixedreality",
  "ReadMePath": "sdk/mixedreality/azure-mixedreality-authentication/README.md",
  "ChangeLogPath": "sdk/mixedreality/azure-mixedreality-authentication/CHANGELOG.md",
  "Group": "com.azure",
  "SdkType": "client",
  "IsNewSdk": true,
  "ArtifactName": "azure-mixedreality-authentication",
  "ReleaseStatus": "2026-01-29",
  "IncludedForValidation": false,
  "AdditionalValidationPackages": null,
  "ArtifactDetails": {
    "triggeringPaths": [
      "/sdk/mixedreality/ci.yml"
    ],
    "groupId": "com.azure",
    "safeName": "azuremixedrealityauthentication",
    "name": "azure-mixedreality-authentication",
    "releaseInBatch": "${{ parameters.release_azuremixedrealityauthentication }}"
  },
  "CIParameters": {
    "CIMatrixConfigs": []
  },
  "SpecProjectPath": null,
  "Namespaces": [
    "com.azure.mixedreality.authentication"
  ],
  "CIMatrixConfigs": [],
  "DependentPackages": null
}
