{
  "Name": "azure-resourcemanager-monitor-slis",
  "Version": "1.0.0-beta.2",
  "DevVersion": null,
  "DirectoryPath": "sdk/monitor/azure-resourcemanager-monitor-slis",
  "ServiceDirectory": "monitor",
  "ReadMePath": "sdk/monitor/azure-resourcemanager-monitor-slis/README.md",
  "ChangeLogPath": "sdk/monitor/azure-resourcemanager-monitor-slis/CHANGELOG.md",
  "Group": "com.azure.resourcemanager",
  "SdkType": "mgmt",
  "IsNewSdk": true,
  "ArtifactName": "azure-resourcemanager-monitor-slis",
  "ReleaseStatus": "2026-06-02",
  "IncludedForValidation": false,
  "AdditionalValidationPackages": [
    "com.azure:azure-monitor-query-perf",
    "com.azure:azure-monitor-ingestion-perf",
    "com.azure:perf-test-core"
  ],
  "ArtifactDetails": {
    "name": "azure-resourcemanager-monitor-slis",
    "triggeringPaths": [
      "/sdk/monitor/ci.yml"
    ],
    "releaseInBatch": "${{ parameters.release_azureresourcemanagermonitorslis }}",
    "groupId": "com.azure.resourcemanager",
    "safeName": "azureresourcemanagermonitorslis"
  },
  "CIParameters": {
    "CIMatrixConfigs": []
  },
  "SpecProjectPath": "specification/monitoringservice/resource-manager/Microsoft.Monitor/Slis",
  "Namespaces": [
    "com.azure.resourcemanager.monitor.slis",
    "com.azure.resourcemanager.monitor.slis.fluent",
    "com.azure.resourcemanager.monitor.slis.fluent.models",
    "com.azure.resourcemanager.monitor.slis.models"
  ]
}
